<?xml version="1.0" encoding="utf-8" ?><dwsync><file name="Changelog.txt" server="174.132.79.252//www/" local="3380972160" remote="20560841344" /><file name="advanced-cache.php" server="174.132.79.252//www/" local="3380972160" remote="20560841344" /><file name="ossdl-cdn.php" server="174.132.79.252//www/" local="3380972160" remote="20560841344" /><file name="readme.txt" server="174.132.79.252//www/" local="3380972160" remote="20560841344" /><file name="wp-cache-base.php" server="174.132.79.252//www/" local="3380972160" remote="20560841344" /><file name="wp-cache-config-sample.php" server="174.132.79.252//www/" local="3380972160" remote="20560841344" /><file name="wp-cache-phase1.php" server="174.132.79.252//www/" local="3380972160" remote="20560841344" /><file name="wp-cache-phase2.php" server="174.132.79.252//www/" local="3380972160" remote="11970906752" /><file name="wp-cache.php" server="174.132.79.252//www/" local="3380972160" remote="20560841344" /><file name="wp-super-cache.pot" server="174.132.79.252//www/" local="3380972160" remote="20560841344" /></dwsync>