<?xml version="1.0" encoding="utf-8" ?><dwsync><file name="Adbrite.php" server="174.132.79.252//www/" local="3368204700" remote="20548073884" /><file name="Adgridwork.php" server="174.132.79.252//www/" local="3368204700" remote="20548073884" /><file name="Adify.php" server="174.132.79.252//www/" local="3368204700" remote="20548073884" /><file name="Adpinion.php" server="174.132.79.252//www/" local="3368204700" remote="20548073884" /><file name="Adroll.php" server="174.132.79.252//www/" local="3368204700" remote="20548073884" /><file name="Adsense.php" server="174.132.79.252//www/" local="3368204700" remote="20548073884" /><file name="Chitika.php" server="174.132.79.252//www/" local="3368204700" remote="20548073884" /><file name="Cj.php" server="174.132.79.252//www/" local="3368204700" remote="20548073884" /><file name="Crispads.php" server="174.132.79.252//www/" local="3368204700" remote="20548073884" /><file name="Openx.php" server="174.132.79.252//www/" local="3368204700" remote="20548073884" /><file name="Shoppingads.php" server="174.132.79.252//www/" local="3368204700" remote="20548073884" /><file name="Widgetbucks.php" server="174.132.79.252//www/" local="3368204700" remote="20548073884" /><file name="Ypn.php" server="174.132.79.252//www/" local="3368204700" remote="20548073884" /></dwsync>